Metadata-Version: 2.1
Name: qworktree
Version: 0.6.1
Summary: qworktree generator of main Qt .pro file for a full worktree
Home-page: http://github.com/HeeroYui/qworktree
Author: Edouard DUPIN
Author-email: yui.heero@gmail.com
License: MPL-2
Keywords: qmake worktree build qt
Platform: UNKNOWN
Classifier: Development Status :: 5 - Production/Stable
Classifier: License :: OSI Approved :: Mozilla Public License 2.0 (MPL 2.0)
Classifier: Programming Language :: Python
Classifier: Topic :: Software Development :: Build Tools
